raggedy/__init__.py
raggedy/exceptions.py
raggedy/chat/attach.py
raggedy/chat/chat.py
raggedy/chat/new_chat.py
raggedy/chat/subclasses/ollama.py
raggedy/document/doctype.py
raggedy/document/document.py
raggedy/document/pdf/types.py
raggedy/document/pdf/utils.py
raggedy/document/subclasses/audio.py
raggedy/document/subclasses/textual.py
raggedy/document/subclasses/visual.py
raggedy-1.0.1.dist-info/METADATA
raggedy-1.0.1.dist-info/WHEEL
raggedy-1.0.1.dist-info/licenses/LICENSE
raggedy-1.0.1.dist-info/RECORD
